dffml_model_daal4py/__init__.py
dffml_model_daal4py/daal4pylr.py
dffml_model_daal4py/version.py
tests/__init__.py
tests/test_lr.py
tests/test_lr_integration.py
dffml_model_daal4py-0.1.0.post0.dist-info/LICENSE
dffml_model_daal4py-0.1.0.post0.dist-info/METADATA
dffml_model_daal4py-0.1.0.post0.dist-info/WHEEL
dffml_model_daal4py-0.1.0.post0.dist-info/entry_points.txt
dffml_model_daal4py-0.1.0.post0.dist-info/top_level.txt
dffml_model_daal4py-0.1.0.post0.dist-info/RECORD
