Metadata-Version: 2.1
Name: dffml-model-daal4py
Version: 0.1.0.post0
Summary: DFFML model daal4py
Home-page: https://github.com/intel/dffml-model-daal4py
Author: Ch.M.Hashim
Author-email: hashimchaudry23@gmail.com
Maintainer: John Andersen
Maintainer-email: john.s.andersen@intel.com
License: MIT
Keywords: dffml
Platform: UNKNOWN
Classifier: Development Status :: 3 - Alpha
Classifier: Intended Audience :: Developers
Classifier: License :: OSI Approved :: MIT License
Classifier: Natural Language :: English
Classifier: Operating System :: OS Independent
Classifier: Programming Language :: Python :: 3 :: Only
Classifier: Programming Language :: Python :: 3.7
Classifier: Programming Language :: Python :: Implementation :: CPython
Classifier: Programming Language :: Python :: Implementation :: PyPy
License-File: LICENSE
Requires-Dist: dffml (>=0.4.0)
Requires-Dist: pandas (>=0.25.0)
Requires-Dist: joblib (>=0.13.2)
Requires-Dist: numpy (>=1.19.2)
Requires-Dist: daal4py (>=2021.1)
